{
  "accelerator_path": "/private/tmp/prometheus-r176-overlay-0c9614cd034d8621/qiskit/_accelerate.abi3.so",
  "accelerator_sha256": "0c9614cd034d8621047f3bc78702695eea2f448d8a84fabce4729fadfbcdf5ea",
  "case_summaries": [
    {
      "case_id": "edge_0_1_m008ulp",
      "case_summary_hash": "5954c130ee96963b90ffd5d1a7d5d5ed706d0a36ab754a1de3d9fbe1d2893515",
      "elapsed_ns_median": 15625.0,
      "elapsed_ns_p95_nearest_rank": 18459,
      "error_map_descriptor": {
        "case_id": "edge_0_1_m008ulp",
        "construction": "R159 operation-error bits, declared accumulation, optional declared ULP shift",
        "mode": "descending_f64",
        "payload_hash": "431325a579fd6d28f4bdf2e3a06a572b3cc393de8d4aec3bf9f1d1bcf4a0435e",
        "rows": [
          {
            "base_bits": 4573474103581024862,
            "key": [
              0,
              0
            ],
            "perturbed": false,
            "value_bits": 4573474103581024862
          },
          {
            "base_bits": 4567100593048839616,
            "key": [
              0,
              1
            ],
            "perturbed": true,
            "value_bits": 4567100593048839608
          },
          {
            "base_bits": 4566947158837165289,
            "key": [
              1,
              1
            ],
            "perturbed": false,
            "value_bits": 4566947158837165289
          },
          {
            "base_bits": 4567100593048839616,
            "key": [
              1,
              0
            ],
            "perturbed": false,
            "value_bits": 4567100593048839616
          },
          {
            "base_bits": 4565693368545587072,
            "key": [
              1,
              2
            ],
            "perturbed": false,
            "value_bits": 4565693368545587072
          },
          {
            "base_bits": 4565472299965932064,
            "key": [
              1,
              3
            ],
            "perturbed": false,
            "value_bits": 4565472299965932064
          },
          {
            "base_bits": 4566736071831264124,
            "key": [
              2,
              2
            ],
            "perturbed": false,
            "value_bits": 4566736071831264124
          },
          {
            "base_bits": 4565693368545587072,
            "key": [
              2,
              1
            ],
            "perturbed": false,
            "value_bits": 4565693368545587072
          },
          {
            "base_bits": 4567570890438721935,
            "key": [
              3,
              3
            ],
            "perturbed": false,
            "value_bits": 4567570890438721935
          },
          {
            "base_bits": 4565472299965932064,
            "key": [
              3,
              1
            ],
            "perturbed": false,
            "value_bits": 4565472299965932064
          },
          {
            "base_bits": 4569393841727551520,
            "key": [
              3,
              5
            ],
            "perturbed": false,
            "value_bits": 4569393841727551520
          },
          {
            "base_bits": 4566733819296185530,
            "key": [
              4,
              4
            ],
            "perturbed": false,
            "value_bits": 4566733819296185530
          },
          {
            "base_bits": 4565718906690324480,
            "key": [
              4,
              5
            ],
            "perturbed": false,
            "value_bits": 4565718906690324480
          },
          {
            "base_bits": 4567912515276044964,
            "key": [
              5,
              5
            ],
            "perturbed": false,
            "value_bits": 4567912515276044964
          },
          {
            "base_bits": 4569393841727551520,
            "key": [
              5,
              3
            ],
            "perturbed": false,
            "value_bits": 4569393841727551520
          },
          {
            "base_bits": 4565718906690324480,
            "key": [
              5,
              4
            ],
            "perturbed": false,
            "value_bits": 4565718906690324480
          },
          {
            "base_bits": 4568291497957912992,
            "key": [
              5,
              6
            ],
            "perturbed": false,
            "value_bits": 4568291497957912992
          },
          {
            "base_bits": 4568277749028269718,
            "key": [
              6,
              6
            ],
            "perturbed": false,
            "value_bits": 4568277749028269718
          },
          {
            "base_bits": 4568291497957912992,
            "key": [
              6,
              5
            ],
            "perturbed": false,
            "value_bits": 4568291497957912992
          }
        ]
      },
      "exact_leaf_oracle": {
        "feasible_mapping_count": 8,
        "minimizer_count": 1,
        "minimizer_vectors": [
          [
            6,
            5,
            4,
            3,
            2,
            1,
            0
          ]
        ],
        "minimum_gap_float": 1.3877787807814457e-17,
        "minimum_gap_fraction": "1/72057594037927936",
        "minimum_gap_ulp_ratio": 0.5,
        "minimum_score_fraction": "100963302183985969/576460752303423488",
        "second_distinct_score_fraction": "100963302183985977/576460752303423488"
      },
      "matches_expected": 8,
      "recorded_call_count": 8
    },
    {
      "case_id": "edge_0_1_m001ulp",
      "case_summary_hash": "778652162a433bd58edd23c81fa20f310c1f9487bd35af7c44c36e7aaf5da23b",
      "elapsed_ns_median": 15312.5,
      "elapsed_ns_p95_nearest_rank": 17083,
      "error_map_descriptor": {
        "case_id": "edge_0_1_m001ulp",
        "construction": "R159 operation-error bits, declared accumulation, optional declared ULP shift",
        "mode": "descending_f64",
        "payload_hash": "ac9f702a3c9a3903de6dc3c397e2ea2e5bf6fc3675b0aaf45d09a71545a5fd7e",
        "rows": [
          {
            "base_bits": 4573474103581024862,
            "key": [
              0,
              0
            ],
            "perturbed": false,
            "value_bits": 4573474103581024862
          },
          {
            "base_bits": 4567100593048839616,
            "key": [
              0,
              1
            ],
            "perturbed": true,
            "value_bits": 4567100593048839615
          },
          {
            "base_bits": 4566947158837165289,
            "key": [
              1,
              1
            ],
            "perturbed": false,
            "value_bits": 4566947158837165289
          },
          {
            "base_bits": 4567100593048839616,
            "key": [
              1,
              0
            ],
            "perturbed": false,
            "value_bits": 4567100593048839616
          },
          {
            "base_bits": 4565693368545587072,
            "key": [
              1,
              2
            ],
            "perturbed": false,
            "value_bits": 4565693368545587072
          },
          {
            "base_bits": 4565472299965932064,
            "key": [
              1,
              3
            ],
            "perturbed": false,
            "value_bits": 4565472299965932064
          },
          {
            "base_bits": 4566736071831264124,
            "key": [
              2,
              2
            ],
            "perturbed": false,
            "value_bits": 4566736071831264124
          },
          {
            "base_bits": 4565693368545587072,
            "key": [
              2,
              1
            ],
            "perturbed": false,
            "value_bits": 4565693368545587072
          },
          {
            "base_bits": 4567570890438721935,
            "key": [
              3,
              3
            ],
            "perturbed": false,
            "value_bits": 4567570890438721935
          },
          {
            "base_bits": 4565472299965932064,
            "key": [
              3,
              1
            ],
            "perturbed": false,
            "value_bits": 4565472299965932064
          },
          {
            "base_bits": 4569393841727551520,
            "key": [
              3,
              5
            ],
            "perturbed": false,
            "value_bits": 4569393841727551520
          },
          {
            "base_bits": 4566733819296185530,
            "key": [
              4,
              4
            ],
            "perturbed": false,
            "value_bits": 4566733819296185530
          },
          {
            "base_bits": 4565718906690324480,
            "key": [
              4,
              5
            ],
            "perturbed": false,
            "value_bits": 4565718906690324480
          },
          {
            "base_bits": 4567912515276044964,
            "key": [
              5,
              5
            ],
            "perturbed": false,
            "value_bits": 4567912515276044964
          },
          {
            "base_bits": 4569393841727551520,
            "key": [
              5,
              3
            ],
            "perturbed": false,
            "value_bits": 4569393841727551520
          },
          {
            "base_bits": 4565718906690324480,
            "key": [
              5,
              4
            ],
            "perturbed": false,
            "value_bits": 4565718906690324480
          },
          {
            "base_bits": 4568291497957912992,
            "key": [
              5,
              6
            ],
            "perturbed": false,
            "value_bits": 4568291497957912992
          },
          {
            "base_bits": 4568277749028269718,
            "key": [
              6,
              6
            ],
            "perturbed": false,
            "value_bits": 4568277749028269718
          },
          {
            "base_bits": 4568291497957912992,
            "key": [
              6,
              5
            ],
            "perturbed": false,
            "value_bits": 4568291497957912992
          }
        ]
      },
      "exact_leaf_oracle": {
        "feasible_mapping_count": 8,
        "minimizer_count": 1,
        "minimizer_vectors": [
          [
            6,
            5,
            4,
            3,
            2,
            1,
            0
          ]
        ],
        "minimum_gap_float": 8.673617379884035e-19,
        "minimum_gap_fraction": "1/1152921504606846976",
        "minimum_gap_ulp_ratio": 0.03125,
        "minimum_score_fraction": "25240825545996495/144115188075855872",
        "second_distinct_score_fraction": "201926604367971961/1152921504606846976"
      },
      "matches_expected": 8,
      "recorded_call_count": 8
    },
    {
      "case_id": "edge_1_0_p001ulp",
      "case_summary_hash": "18f7798aeb073614d02eeee1c58056a79037991d70b2207daa2dc34d7916cc36",
      "elapsed_ns_median": 14874.5,
      "elapsed_ns_p95_nearest_rank": 15583,
      "error_map_descriptor": {
        "case_id": "edge_1_0_p001ulp",
        "construction": "R159 operation-error bits, declared accumulation, optional declared ULP shift",
        "mode": "descending_f64",
        "payload_hash": "7b3a90b7a114099c47dabbfdfa4b46f88d656257bedf36b6f49dd82b823f7a1f",
        "rows": [
          {
            "base_bits": 4573474103581024862,
            "key": [
              0,
              0
            ],
            "perturbed": false,
            "value_bits": 4573474103581024862
          },
          {
            "base_bits": 4567100593048839616,
            "key": [
              0,
              1
            ],
            "perturbed": false,
            "value_bits": 4567100593048839616
          },
          {
            "base_bits": 4566947158837165289,
            "key": [
              1,
              1
            ],
            "perturbed": false,
            "value_bits": 4566947158837165289
          },
          {
            "base_bits": 4567100593048839616,
            "key": [
              1,
              0
            ],
            "perturbed": true,
            "value_bits": 4567100593048839617
          },
          {
            "base_bits": 4565693368545587072,
            "key": [
              1,
              2
            ],
            "perturbed": false,
            "value_bits": 4565693368545587072
          },
          {
            "base_bits": 4565472299965932064,
            "key": [
              1,
              3
            ],
            "perturbed": false,
            "value_bits": 4565472299965932064
          },
          {
            "base_bits": 4566736071831264124,
            "key": [
              2,
              2
            ],
            "perturbed": false,
            "value_bits": 4566736071831264124
          },
          {
            "base_bits": 4565693368545587072,
            "key": [
              2,
              1
            ],
            "perturbed": false,
            "value_bits": 4565693368545587072
          },
          {
            "base_bits": 4567570890438721935,
            "key": [
              3,
              3
            ],
            "perturbed": false,
            "value_bits": 4567570890438721935
          },
          {
            "base_bits": 4565472299965932064,
            "key": [
              3,
              1
            ],
            "perturbed": false,
            "value_bits": 4565472299965932064
          },
          {
            "base_bits": 4569393841727551520,
            "key": [
              3,
              5
            ],
            "perturbed": false,
            "value_bits": 4569393841727551520
          },
          {
            "base_bits": 4566733819296185530,
            "key": [
              4,
              4
            ],
            "perturbed": false,
            "value_bits": 4566733819296185530
          },
          {
            "base_bits": 4565718906690324480,
            "key": [
              4,
              5
            ],
            "perturbed": false,
            "value_bits": 4565718906690324480
          },
          {
            "base_bits": 4567912515276044964,
            "key": [
              5,
              5
            ],
            "perturbed": false,
            "value_bits": 4567912515276044964
          },
          {
            "base_bits": 4569393841727551520,
            "key": [
              5,
              3
            ],
            "perturbed": false,
            "value_bits": 4569393841727551520
          },
          {
            "base_bits": 4565718906690324480,
            "key": [
              5,
              4
            ],
            "perturbed": false,
            "value_bits": 4565718906690324480
          },
          {
            "base_bits": 4568291497957912992,
            "key": [
              5,
              6
            ],
            "perturbed": false,
            "value_bits": 4568291497957912992
          },
          {
            "base_bits": 4568277749028269718,
            "key": [
              6,
              6
            ],
            "perturbed": false,
            "value_bits": 4568277749028269718
          },
          {
            "base_bits": 4568291497957912992,
            "key": [
              6,
              5
            ],
            "perturbed": false,
            "value_bits": 4568291497957912992
          }
        ]
      },
      "exact_leaf_oracle": {
        "feasible_mapping_count": 8,
        "minimizer_count": 1,
        "minimizer_vectors": [
          [
            6,
            5,
            4,
            3,
            2,
            1,
            0
          ]
        ],
        "minimum_gap_float": 2.6020852139652106e-18,
        "minimum_gap_fraction": "3/1152921504606846976",
        "minimum_gap_ulp_ratio": 0.09375,
        "minimum_score_fraction": "201926604367971963/1152921504606846976",
        "second_distinct_score_fraction": "100963302183985983/576460752303423488"
      },
      "matches_expected": 8,
      "recorded_call_count": 8
    },
    {
      "case_id": "edge_1_0_p008ulp",
      "case_summary_hash": "81bbc8ce5ba319660596d673384d3fd90ff408e05ac403892c167a32dfb07190",
      "elapsed_ns_median": 14771.0,
      "elapsed_ns_p95_nearest_rank": 15375,
      "error_map_descriptor": {
        "case_id": "edge_1_0_p008ulp",
        "construction": "R159 operation-error bits, declared accumulation, optional declared ULP shift",
        "mode": "descending_f64",
        "payload_hash": "441dfa7ece0f3d62c95806c5b4909107f3561aada3f54d2bb9a0a40c0f4f013b",
        "rows": [
          {
            "base_bits": 4573474103581024862,
            "key": [
              0,
              0
            ],
            "perturbed": false,
            "value_bits": 4573474103581024862
          },
          {
            "base_bits": 4567100593048839616,
            "key": [
              0,
              1
            ],
            "perturbed": false,
            "value_bits": 4567100593048839616
          },
          {
            "base_bits": 4566947158837165289,
            "key": [
              1,
              1
            ],
            "perturbed": false,
            "value_bits": 4566947158837165289
          },
          {
            "base_bits": 4567100593048839616,
            "key": [
              1,
              0
            ],
            "perturbed": true,
            "value_bits": 4567100593048839624
          },
          {
            "base_bits": 4565693368545587072,
            "key": [
              1,
              2
            ],
            "perturbed": false,
            "value_bits": 4565693368545587072
          },
          {
            "base_bits": 4565472299965932064,
            "key": [
              1,
              3
            ],
            "perturbed": false,
            "value_bits": 4565472299965932064
          },
          {
            "base_bits": 4566736071831264124,
            "key": [
              2,
              2
            ],
            "perturbed": false,
            "value_bits": 4566736071831264124
          },
          {
            "base_bits": 4565693368545587072,
            "key": [
              2,
              1
            ],
            "perturbed": false,
            "value_bits": 4565693368545587072
          },
          {
            "base_bits": 4567570890438721935,
            "key": [
              3,
              3
            ],
            "perturbed": false,
            "value_bits": 4567570890438721935
          },
          {
            "base_bits": 4565472299965932064,
            "key": [
              3,
              1
            ],
            "perturbed": false,
            "value_bits": 4565472299965932064
          },
          {
            "base_bits": 4569393841727551520,
            "key": [
              3,
              5
            ],
            "perturbed": false,
            "value_bits": 4569393841727551520
          },
          {
            "base_bits": 4566733819296185530,
            "key": [
              4,
              4
            ],
            "perturbed": false,
            "value_bits": 4566733819296185530
          },
          {
            "base_bits": 4565718906690324480,
            "key": [
              4,
              5
            ],
            "perturbed": false,
            "value_bits": 4565718906690324480
          },
          {
            "base_bits": 4567912515276044964,
            "key": [
              5,
              5
            ],
            "perturbed": false,
            "value_bits": 4567912515276044964
          },
          {
            "base_bits": 4569393841727551520,
            "key": [
              5,
              3
            ],
            "perturbed": false,
            "value_bits": 4569393841727551520
          },
          {
            "base_bits": 4565718906690324480,
            "key": [
              5,
              4
            ],
            "perturbed": false,
            "value_bits": 4565718906690324480
          },
          {
            "base_bits": 4568291497957912992,
            "key": [
              5,
              6
            ],
            "perturbed": false,
            "value_bits": 4568291497957912992
          },
          {
            "base_bits": 4568277749028269718,
            "key": [
              6,
              6
            ],
            "perturbed": false,
            "value_bits": 4568277749028269718
          },
          {
            "base_bits": 4568291497957912992,
            "key": [
              6,
              5
            ],
            "perturbed": false,
            "value_bits": 4568291497957912992
          }
        ]
      },
      "exact_leaf_oracle": {
        "feasible_mapping_count": 8,
        "minimizer_count": 1,
        "minimizer_vectors": [
          [
            6,
            5,
            4,
            3,
            2,
            1,
            0
          ]
        ],
        "minimum_gap_float": 1.3877787807814457e-17,
        "minimum_gap_fraction": "1/72057594037927936",
        "minimum_gap_ulp_ratio": 0.5,
        "minimum_score_fraction": "100963302183985985/576460752303423488",
        "second_distinct_score_fraction": "100963302183985993/576460752303423488"
      },
      "matches_expected": 8,
      "recorded_call_count": 8
    },
    {
      "case_id": "edge_1_2_m001ulp",
      "case_summary_hash": "0cb24b39f24c358042631fd4bb7d58ff7b95395a4d3a395ebc0cc30fb59415ac",
      "elapsed_ns_median": 14812.0,
      "elapsed_ns_p95_nearest_rank": 15208,
      "error_map_descriptor": {
        "case_id": "edge_1_2_m001ulp",
        "construction": "R159 operation-error bits, declared accumulation, optional declared ULP shift",
        "mode": "descending_f64",
        "payload_hash": "4da96593d8d5f960413c4d60ddc9753e7e54024d523f5f69f2758a6360d33f5e",
        "rows": [
          {
            "base_bits": 4573474103581024862,
            "key": [
              0,
              0
            ],
            "perturbed": false,
            "value_bits": 4573474103581024862
          },
          {
            "base_bits": 4567100593048839616,
            "key": [
              0,
              1
            ],
            "perturbed": false,
            "value_bits": 4567100593048839616
          },
          {
            "base_bits": 4566947158837165289,
            "key": [
              1,
              1
            ],
            "perturbed": false,
            "value_bits": 4566947158837165289
          },
          {
            "base_bits": 4567100593048839616,
            "key": [
              1,
              0
            ],
            "perturbed": false,
            "value_bits": 4567100593048839616
          },
          {
            "base_bits": 4565693368545587072,
            "key": [
              1,
              2
            ],
            "perturbed": true,
            "value_bits": 4565693368545587071
          },
          {
            "base_bits": 4565472299965932064,
            "key": [
              1,
              3
            ],
            "perturbed": false,
            "value_bits": 4565472299965932064
          },
          {
            "base_bits": 4566736071831264124,
            "key": [
              2,
              2
            ],
            "perturbed": false,
            "value_bits": 4566736071831264124
          },
          {
            "base_bits": 4565693368545587072,
            "key": [
              2,
              1
            ],
            "perturbed": false,
            "value_bits": 4565693368545587072
          },
          {
            "base_bits": 4567570890438721935,
            "key": [
              3,
              3
            ],
            "perturbed": false,
            "value_bits": 4567570890438721935
          },
          {
            "base_bits": 4565472299965932064,
            "key": [
              3,
              1
            ],
            "perturbed": false,
            "value_bits": 4565472299965932064
          },
          {
            "base_bits": 4569393841727551520,
            "key": [
              3,
              5
            ],
            "perturbed": false,
            "value_bits": 4569393841727551520
          },
          {
            "base_bits": 4566733819296185530,
            "key": [
              4,
              4
            ],
            "perturbed": false,
            "value_bits": 4566733819296185530
          },
          {
            "base_bits": 4565718906690324480,
            "key": [
              4,
              5
            ],
            "perturbed": false,
            "value_bits": 4565718906690324480
          },
          {
            "base_bits": 4567912515276044964,
            "key": [
              5,
              5
            ],
            "perturbed": false,
            "value_bits": 4567912515276044964
          },
          {
            "base_bits": 4569393841727551520,
            "key": [
              5,
              3
            ],
            "perturbed": false,
            "value_bits": 4569393841727551520
          },
          {
            "base_bits": 4565718906690324480,
            "key": [
              5,
              4
            ],
            "perturbed": false,
            "value_bits": 4565718906690324480
          },
          {
            "base_bits": 4568291497957912992,
            "key": [
              5,
              6
            ],
            "perturbed": false,
            "value_bits": 4568291497957912992
          },
          {
            "base_bits": 4568277749028269718,
            "key": [
              6,
              6
            ],
            "perturbed": false,
            "value_bits": 4568277749028269718
          },
          {
            "base_bits": 4568291497957912992,
            "key": [
              6,
              5
            ],
            "perturbed": false,
            "value_bits": 4568291497957912992
          }
        ]
      },
      "exact_leaf_oracle": {
        "feasible_mapping_count": 8,
        "minimizer_count": 1,
        "minimizer_vectors": [
          [
            6,
            5,
            4,
            3,
            2,
            1,
            0
          ]
        ],
        "minimum_gap_float": 1.3010426069826053e-18,
        "minimum_gap_fraction": "3/2305843009213693952",
        "minimum_gap_ulp_ratio": 0.046875,
        "minimum_score_fraction": "25240825545996495/144115188075855872",
        "second_distinct_score_fraction": "403853208735943923/2305843009213693952"
      },
      "matches_expected": 8,
      "recorded_call_count": 8
    },
    {
      "case_id": "edge_2_1_p001ulp",
      "case_summary_hash": "5c005115bc3990a2410d0ee0ff75ec9c72f67b51099f03dd6c9a7f9d981eec0b",
      "elapsed_ns_median": 14771.0,
      "elapsed_ns_p95_nearest_rank": 15125,
      "error_map_descriptor": {
        "case_id": "edge_2_1_p001ulp",
        "construction": "R159 operation-error bits, declared accumulation, optional declared ULP shift",
        "mode": "descending_f64",
        "payload_hash": "6f857c86da7e8c5cf82806f3361aa4a9b2467bc8982ef8f97d61178ee46bf13d",
        "rows": [
          {
            "base_bits": 4573474103581024862,
            "key": [
              0,
              0
            ],
            "perturbed": false,
            "value_bits": 4573474103581024862
          },
          {
            "base_bits": 4567100593048839616,
            "key": [
              0,
              1
            ],
            "perturbed": false,
            "value_bits": 4567100593048839616
          },
          {
            "base_bits": 4566947158837165289,
            "key": [
              1,
              1
            ],
            "perturbed": false,
            "value_bits": 4566947158837165289
          },
          {
            "base_bits": 4567100593048839616,
            "key": [
              1,
              0
            ],
            "perturbed": false,
            "value_bits": 4567100593048839616
          },
          {
            "base_bits": 4565693368545587072,
            "key": [
              1,
              2
            ],
            "perturbed": false,
            "value_bits": 4565693368545587072
          },
          {
            "base_bits": 4565472299965932064,
            "key": [
              1,
              3
            ],
            "perturbed": false,
            "value_bits": 4565472299965932064
          },
          {
            "base_bits": 4566736071831264124,
            "key": [
              2,
              2
            ],
            "perturbed": false,
            "value_bits": 4566736071831264124
          },
          {
            "base_bits": 4565693368545587072,
            "key": [
              2,
              1
            ],
            "perturbed": true,
            "value_bits": 4565693368545587073
          },
          {
            "base_bits": 4567570890438721935,
            "key": [
              3,
              3
            ],
            "perturbed": false,
            "value_bits": 4567570890438721935
          },
          {
            "base_bits": 4565472299965932064,
            "key": [
              3,
              1
            ],
            "perturbed": false,
            "value_bits": 4565472299965932064
          },
          {
            "base_bits": 4569393841727551520,
            "key": [
              3,
              5
            ],
            "perturbed": false,
            "value_bits": 4569393841727551520
          },
          {
            "base_bits": 4566733819296185530,
            "key": [
              4,
              4
            ],
            "perturbed": false,
            "value_bits": 4566733819296185530
          },
          {
            "base_bits": 4565718906690324480,
            "key": [
              4,
              5
            ],
            "perturbed": false,
            "value_bits": 4565718906690324480
          },
          {
            "base_bits": 4567912515276044964,
            "key": [
              5,
              5
            ],
            "perturbed": false,
            "value_bits": 4567912515276044964
          },
          {
            "base_bits": 4569393841727551520,
            "key": [
              5,
              3
            ],
            "perturbed": false,
            "value_bits": 4569393841727551520
          },
          {
            "base_bits": 4565718906690324480,
            "key": [
              5,
              4
            ],
            "perturbed": false,
            "value_bits": 4565718906690324480
          },
          {
            "base_bits": 4568291497957912992,
            "key": [
              5,
              6
            ],
            "perturbed": false,
            "value_bits": 4568291497957912992
          },
          {
            "base_bits": 4568277749028269718,
            "key": [
              6,
              6
            ],
            "perturbed": false,
            "value_bits": 4568277749028269718
          },
          {
            "base_bits": 4568291497957912992,
            "key": [
              6,
              5
            ],
            "perturbed": false,
            "value_bits": 4568291497957912992
          }
        ]
      },
      "exact_leaf_oracle": {
        "feasible_mapping_count": 8,
        "minimizer_count": 1,
        "minimizer_vectors": [
          [
            6,
            5,
            4,
            3,
            2,
            1,
            0
          ]
        ],
        "minimum_gap_float": 1.3010426069826053e-18,
        "minimum_gap_fraction": "3/2305843009213693952",
        "minimum_gap_ulp_ratio": 0.046875,
        "minimum_score_fraction": "403853208735943925/2305843009213693952",
        "second_distinct_score_fraction": "50481651091992991/288230376151711744"
      },
      "matches_expected": 8,
      "recorded_call_count": 8
    },
    {
      "case_id": "edge_2_1_p008ulp",
      "case_summary_hash": "192a0ed635fadbdec46e00c35b81d068e3071b361d7c4ec8df849e6db5141383",
      "elapsed_ns_median": 14771.0,
      "elapsed_ns_p95_nearest_rank": 15083,
      "error_map_descriptor": {
        "case_id": "edge_2_1_p008ulp",
        "construction": "R159 operation-error bits, declared accumulation, optional declared ULP shift",
        "mode": "descending_f64",
        "payload_hash": "0ba8e42c6e27d10c2ced128b6018016803d09ba9ad7221062d5a24f504e85cd1",
        "rows": [
          {
            "base_bits": 4573474103581024862,
            "key": [
              0,
              0
            ],
            "perturbed": false,
            "value_bits": 4573474103581024862
          },
          {
            "base_bits": 4567100593048839616,
            "key": [
              0,
              1
            ],
            "perturbed": false,
            "value_bits": 4567100593048839616
          },
          {
            "base_bits": 4566947158837165289,
            "key": [
              1,
              1
            ],
            "perturbed": false,
            "value_bits": 4566947158837165289
          },
          {
            "base_bits": 4567100593048839616,
            "key": [
              1,
              0
            ],
            "perturbed": false,
            "value_bits": 4567100593048839616
          },
          {
            "base_bits": 4565693368545587072,
            "key": [
              1,
              2
            ],
            "perturbed": false,
            "value_bits": 4565693368545587072
          },
          {
            "base_bits": 4565472299965932064,
            "key": [
              1,
              3
            ],
            "perturbed": false,
            "value_bits": 4565472299965932064
          },
          {
            "base_bits": 4566736071831264124,
            "key": [
              2,
              2
            ],
            "perturbed": false,
            "value_bits": 4566736071831264124
          },
          {
            "base_bits": 4565693368545587072,
            "key": [
              2,
              1
            ],
            "perturbed": true,
            "value_bits": 4565693368545587080
          },
          {
            "base_bits": 4567570890438721935,
            "key": [
              3,
              3
            ],
            "perturbed": false,
            "value_bits": 4567570890438721935
          },
          {
            "base_bits": 4565472299965932064,
            "key": [
              3,
              1
            ],
            "perturbed": false,
            "value_bits": 4565472299965932064
          },
          {
            "base_bits": 4569393841727551520,
            "key": [
              3,
              5
            ],
            "perturbed": false,
            "value_bits": 4569393841727551520
          },
          {
            "base_bits": 4566733819296185530,
            "key": [
              4,
              4
            ],
            "perturbed": false,
            "value_bits": 4566733819296185530
          },
          {
            "base_bits": 4565718906690324480,
            "key": [
              4,
              5
            ],
            "perturbed": false,
            "value_bits": 4565718906690324480
          },
          {
            "base_bits": 4567912515276044964,
            "key": [
              5,
              5
            ],
            "perturbed": false,
            "value_bits": 4567912515276044964
          },
          {
            "base_bits": 4569393841727551520,
            "key": [
              5,
              3
            ],
            "perturbed": false,
            "value_bits": 4569393841727551520
          },
          {
            "base_bits": 4565718906690324480,
            "key": [
              5,
              4
            ],
            "perturbed": false,
            "value_bits": 4565718906690324480
          },
          {
            "base_bits": 4568291497957912992,
            "key": [
              5,
              6
            ],
            "perturbed": false,
            "value_bits": 4568291497957912992
          },
          {
            "base_bits": 4568277749028269718,
            "key": [
              6,
              6
            ],
            "perturbed": false,
            "value_bits": 4568277749028269718
          },
          {
            "base_bits": 4568291497957912992,
            "key": [
              6,
              5
            ],
            "perturbed": false,
            "value_bits": 4568291497957912992
          }
        ]
      },
      "exact_leaf_oracle": {
        "feasible_mapping_count": 8,
        "minimizer_count": 1,
        "minimizer_vectors": [
          [
            6,
            5,
            4,
            3,
            2,
            1,
            0
          ]
        ],
        "minimum_gap_float": 6.938893903907228e-18,
        "minimum_gap_fraction": "1/144115188075855872",
        "minimum_gap_ulp_ratio": 0.25,
        "minimum_score_fraction": "100963302183985983/576460752303423488",
        "second_distinct_score_fraction": "100963302183985987/576460752303423488"
      },
      "matches_expected": 8,
      "recorded_call_count": 8
    }
  ],
  "contract_payload_hash": "152699e5351af0b612f955759e7c7b8cc0c196a48929c9a2c80860cf603c5991",
  "elapsed_ns_median": 14833.5,
  "elapsed_ns_p95_nearest_rank": 17083,
  "environment": {
    "platform": "macOS-26.5.2-arm64-arm-64bit",
    "python": "3.12.6",
    "pythonpath_head": "/private/tmp/prometheus-r174-20260720/tools",
    "qiskit": "2.4.1",
    "qiskit_aer": "0.17.2",
    "qiskit_ibm_runtime": "0.46.1"
  },
  "identity": "descending_f64",
  "input_qasm_sha256": "ce216610e995b4c8b4bd9de6547ac6069961e1eb8881997aa05e0068ea16ab98",
  "kind": "small-gap",
  "manifest_hash": "42f77c5c63f6e43c70a2301a98855158086b19bc0d26b9564e9577ba2e49e193",
  "mode": "descending_f64",
  "peak_rss": 223019008,
  "peak_rss_unit": "bytes",
  "policy": "rust_fixed_exact_retained_binary64",
  "preregistration": {
    "commit": "79228051",
    "created_at": "2026-07-20T14:25:05Z",
    "discussion": "https://github.com/crystal-tensor/Prometheus-plan/discussions/264"
  },
  "process_id": 47596,
  "process_instance_uuid": "e8bcc61d-c551-4ce3-81d4-c343fd790675",
  "protocol_payload_hash": "cc7563feada3d1eb0b1b54338f1eff34a058e4594892c6155e43d6ef7d3443c8",
  "recorded_call_count": 56,
  "recorded_matches_expected": 56,
  "replay_rows": [
    {
      "case_id": "edge_0_1_m008ulp",
      "elapsed_ns": 15708,
      "error_map_descriptor_hash": "431325a579fd6d28f4bdf2e3a06a572b3cc393de8d4aec3bf9f1d1bcf4a0435e",
      "exact_expected_mapping_vector": [
        6,
        5,
        4,
        3,
        2,
        1,
        0
      ],
      "exact_minimum_gap_ulp_ratio": 0.5,
      "expected_mapping_vector": [
        6,
        5,
        4,
        3,
        2,
        1,
        0
      ],
      "kind": "small-gap",
      "mapping_vector": [
        6,
        5,
        4,
        3,
        2,
        1,
        0
      ],
      "matches_expected": true,
      "mode": "descending_f64",
      "policy": "rust_fixed_exact_retained_binary64",
      "replay_index": 0,
      "row_hash": "25c6a8bfbd879236baa981502439c140a8d7a635c52d77e708ea7084e24bf7c0",
      "simulation_execution_count": 0,
      "source_expected_mapping_vector": [
        6,
        5,
        4,
        3,
        0,
        1,
        2
      ],
      "total_simulated_shots": 0
    },
    {
      "case_id": "edge_0_1_m008ulp",
      "elapsed_ns": 18459,
      "error_map_descriptor_hash": "431325a579fd6d28f4bdf2e3a06a572b3cc393de8d4aec3bf9f1d1bcf4a0435e",
      "exact_expected_mapping_vector": [
        6,
        5,
        4,
        3,
        2,
        1,
        0
      ],
      "exact_minimum_gap_ulp_ratio": 0.5,
      "expected_mapping_vector": [
        6,
        5,
        4,
        3,
        2,
        1,
        0
      ],
      "kind": "small-gap",
      "mapping_vector": [
        6,
        5,
        4,
        3,
        2,
        1,
        0
      ],
      "matches_expected": true,
      "mode": "descending_f64",
      "policy": "rust_fixed_exact_retained_binary64",
      "replay_index": 1,
      "row_hash": "d6eec2ae4b82e49d406e7efc99d96a14b9118c6f64b6f63ae290e50849e09882",
      "simulation_execution_count": 0,
      "source_expected_mapping_vector": [
        6,
        5,
        4,
        3,
        0,
        1,
        2
      ],
      "total_simulated_shots": 0
    },
    {
      "case_id": "edge_0_1_m008ulp",
      "elapsed_ns": 16333,
      "error_map_descriptor_hash": "431325a579fd6d28f4bdf2e3a06a572b3cc393de8d4aec3bf9f1d1bcf4a0435e",
      "exact_expected_mapping_vector": [
        6,
        5,
        4,
        3,
        2,
        1,
        0
      ],
      "exact_minimum_gap_ulp_ratio": 0.5,
      "expected_mapping_vector": [
        6,
        5,
        4,
        3,
        2,
        1,
        0
      ],
      "kind": "small-gap",
      "mapping_vector": [
        6,
        5,
        4,
        3,
        2,
        1,
        0
      ],
      "matches_expected": true,
      "mode": "descending_f64",
      "policy": "rust_fixed_exact_retained_binary64",
      "replay_index": 2,
      "row_hash": "737aa8d99926432154d54160d920a0fce7d4486c394eaff062d0f5f076080ae1",
      "simulation_execution_count": 0,
      "source_expected_mapping_vector": [
        6,
        5,
        4,
        3,
        0,
        1,
        2
      ],
      "total_simulated_shots": 0
    },
    {
      "case_id": "edge_0_1_m008ulp",
      "elapsed_ns": 15542,
      "error_map_descriptor_hash": "431325a579fd6d28f4bdf2e3a06a572b3cc393de8d4aec3bf9f1d1bcf4a0435e",
      "exact_expected_mapping_vector": [
        6,
        5,
        4,
        3,
        2,
        1,
        0
      ],
      "exact_minimum_gap_ulp_ratio": 0.5,
      "expected_mapping_vector": [
        6,
        5,
        4,
        3,
        2,
        1,
        0
      ],
      "kind": "small-gap",
      "mapping_vector": [
        6,
        5,
        4,
        3,
        2,
        1,
        0
      ],
      "matches_expected": true,
      "mode": "descending_f64",
      "policy": "rust_fixed_exact_retained_binary64",
      "replay_index": 3,
      "row_hash": "a1e644915f7b81d01324518b2f8173c4c3094d76522c638894e85819f08fa7a7",
      "simulation_execution_count": 0,
      "source_expected_mapping_vector": [
        6,
        5,
        4,
        3,
        0,
        1,
        2
      ],
      "total_simulated_shots": 0
    },
    {
      "case_id": "edge_0_1_m008ulp",
      "elapsed_ns": 15250,
      "error_map_descriptor_hash": "431325a579fd6d28f4bdf2e3a06a572b3cc393de8d4aec3bf9f1d1bcf4a0435e",
      "exact_expected_mapping_vector": [
        6,
        5,
        4,
        3,
        2,
        1,
        0
      ],
      "exact_minimum_gap_ulp_ratio": 0.5,
      "expected_mapping_vector": [
        6,
        5,
        4,
        3,
        2,
        1,
        0
      ],
      "kind": "small-gap",
      "mapping_vector": [
        6,
        5,
        4,
        3,
        2,
        1,
        0
      ],
      "matches_expected": true,
      "mode": "descending_f64",
      "policy": "rust_fixed_exact_retained_binary64",
      "replay_index": 4,
      "row_hash": "3904feb4336b70c9907740d5c1eb6f6c404f911c4ab8fdfc8172e1b33ab7a4da",
      "simulation_execution_count": 0,
      "source_expected_mapping_vector": [
        6,
        5,
        4,
        3,
        0,
        1,
        2
      ],
      "total_simulated_shots": 0
    },
    {
      "case_id": "edge_0_1_m008ulp",
      "elapsed_ns": 17167,
      "error_map_descriptor_hash": "431325a579fd6d28f4bdf2e3a06a572b3cc393de8d4aec3bf9f1d1bcf4a0435e",
      "exact_expected_mapping_vector": [
        6,
        5,
        4,
        3,
        2,
        1,
        0
      ],
      "exact_minimum_gap_ulp_ratio": 0.5,
      "expected_mapping_vector": [
        6,
        5,
        4,
        3,
        2,
        1,
        0
      ],
      "kind": "small-gap",
      "mapping_vector": [
        6,
        5,
        4,
        3,
        2,
        1,
        0
      ],
      "matches_expected": true,
      "mode": "descending_f64",
      "policy": "rust_fixed_exact_retained_binary64",
      "replay_index": 5,
      "row_hash": "c64025ec1608e88d35a251ad674304e21c80c63531b7db522c894fbde7c6548f",
      "simulation_execution_count": 0,
      "source_expected_mapping_vector": [
        6,
        5,
        4,
        3,
        0,
        1,
        2
      ],
      "total_simulated_shots": 0
    },
    {
      "case_id": "edge_0_1_m008ulp",
      "elapsed_ns": 15250,
      "error_map_descriptor_hash": "431325a579fd6d28f4bdf2e3a06a572b3cc393de8d4aec3bf9f1d1bcf4a0435e",
      "exact_expected_mapping_vector": [
        6,
        5,
        4,
        3,
        2,
        1,
        0
      ],
      "exact_minimum_gap_ulp_ratio": 0.5,
      "expected_mapping_vector": [
        6,
        5,
        4,
        3,
        2,
        1,
        0
      ],
      "kind": "small-gap",
      "mapping_vector": [
        6,
        5,
        4,
        3,
        2,
        1,
        0
      ],
      "matches_expected": true,
      "mode": "descending_f64",
      "policy": "rust_fixed_exact_retained_binary64",
      "replay_index": 6,
      "row_hash": "ffb633df2d8fd1e9b0477f77f2653402fa413a7023463c1017c039bfedc36b84",
      "simulation_execution_count": 0,
      "source_expected_mapping_vector": [
        6,
        5,
        4,
        3,
        0,
        1,
        2
      ],
      "total_simulated_shots": 0
    },
    {
      "case_id": "edge_0_1_m008ulp",
      "elapsed_ns": 15208,
      "error_map_descriptor_hash": "431325a579fd6d28f4bdf2e3a06a572b3cc393de8d4aec3bf9f1d1bcf4a0435e",
      "exact_expected_mapping_vector": [
        6,
        5,
        4,
        3,
        2,
        1,
        0
      ],
      "exact_minimum_gap_ulp_ratio": 0.5,
      "expected_mapping_vector": [
        6,
        5,
        4,
        3,
        2,
        1,
        0
      ],
      "kind": "small-gap",
      "mapping_vector": [
        6,
        5,
        4,
        3,
        2,
        1,
        0
      ],
      "matches_expected": true,
      "mode": "descending_f64",
      "policy": "rust_fixed_exact_retained_binary64",
      "replay_index": 7,
      "row_hash": "e8eb00bc99016fee30f56531120538d31412bd386fceb59b771a18f7da9ae9b6",
      "simulation_execution_count": 0,
      "source_expected_mapping_vector": [
        6,
        5,
        4,
        3,
        0,
        1,
        2
      ],
      "total_simulated_shots": 0
    },
    {
      "case_id": "edge_0_1_m001ulp",
      "elapsed_ns": 17083,
      "error_map_descriptor_hash": "ac9f702a3c9a3903de6dc3c397e2ea2e5bf6fc3675b0aaf45d09a71545a5fd7e",
      "exact_expected_mapping_vector": [
        6,
        5,
        4,
        3,
        2,
        1,
        0
      ],
      "exact_minimum_gap_ulp_ratio": 0.03125,
      "expected_mapping_vector": [
        6,
        5,
        4,
        3,
        2,
        1,
        0
      ],
      "kind": "small-gap",
      "mapping_vector": [
        6,
        5,
        4,
        3,
        2,
        1,
        0
      ],
      "matches_expected": true,
      "mode": "descending_f64",
      "policy": "rust_fixed_exact_retained_binary64",
      "replay_index": 0,
      "row_hash": "a13546b68dfdb17237edb2e6d18af562b29d076bddb69ab394bcefb73064578e",
      "simulation_execution_count": 0,
      "source_expected_mapping_vector": [
        6,
        5,
        4,
        3,
        0,
        1,
        2
      ],
      "total_simulated_shots": 0
    },
    {
      "case_id": "edge_0_1_m001ulp",
      "elapsed_ns": 15666,
      "error_map_descriptor_hash": "ac9f702a3c9a3903de6dc3c397e2ea2e5bf6fc3675b0aaf45d09a71545a5fd7e",
      "exact_expected_mapping_vector": [
        6,
        5,
        4,
        3,
        2,
        1,
        0
      ],
      "exact_minimum_gap_ulp_ratio": 0.03125,
      "expected_mapping_vector": [
        6,
        5,
        4,
        3,
        2,
        1,
        0
      ],
      "kind": "small-gap",
      "mapping_vector": [
        6,
        5,
        4,
        3,
        2,
        1,
        0
      ],
      "matches_expected": true,
      "mode": "descending_f64",
      "policy": "rust_fixed_exact_retained_binary64",
      "replay_index": 1,
      "row_hash": "90bf63731c7ffb4d007160bdbadf79de8a2d14475d15259204a0504d8d0408f9",
      "simulation_execution_count": 0,
      "source_expected_mapping_vector": [
        6,
        5,
        4,
        3,
        0,
        1,
        2
      ],
      "total_simulated_shots": 0
    },
    {
      "case_id": "edge_0_1_m001ulp",
      "elapsed_ns": 15291,
      "error_map_descriptor_hash": "ac9f702a3c9a3903de6dc3c397e2ea2e5bf6fc3675b0aaf45d09a71545a5fd7e",
      "exact_expected_mapping_vector": [
        6,
        5,
        4,
        3,
        2,
        1,
        0
      ],
      "exact_minimum_gap_ulp_ratio": 0.03125,
      "expected_mapping_vector": [
        6,
        5,
        4,
        3,
        2,
        1,
        0
      ],
      "kind": "small-gap",
      "mapping_vector": [
        6,
        5,
        4,
        3,
        2,
        1,
        0
      ],
      "matches_expected": true,
      "mode": "descending_f64",
      "policy": "rust_fixed_exact_retained_binary64",
      "replay_index": 2,
      "row_hash": "7c87f240e765780a9fc537bbbd298656969b0fc01fd5047a6e498273b87b24e6",
      "simulation_execution_count": 0,
      "source_expected_mapping_vector": [
        6,
        5,
        4,
        3,
        0,
        1,
        2
      ],
      "total_simulated_shots": 0
    },
    {
      "case_id": "edge_0_1_m001ulp",
      "elapsed_ns": 15166,
      "error_map_descriptor_hash": "ac9f702a3c9a3903de6dc3c397e2ea2e5bf6fc3675b0aaf45d09a71545a5fd7e",
      "exact_expected_mapping_vector": [
        6,
        5,
        4,
        3,
        2,
        1,
        0
      ],
      "exact_minimum_gap_ulp_ratio": 0.03125,
      "expected_mapping_vector": [
        6,
        5,
        4,
        3,
        2,
        1,
        0
      ],
      "kind": "small-gap",
      "mapping_vector": [
        6,
        5,
        4,
        3,
        2,
        1,
        0
      ],
      "matches_expected": true,
      "mode": "descending_f64",
      "policy": "rust_fixed_exact_retained_binary64",
      "replay_index": 3,
      "row_hash": "71b1decf16dec5f538f6d1afd2c8147a4995268252af66f72bdfa50488d74865",
      "simulation_execution_count": 0,
      "source_expected_mapping_vector": [
        6,
        5,
        4,
        3,
        0,
        1,
        2
      ],
      "total_simulated_shots": 0
    },
    {
      "case_id": "edge_0_1_m001ulp",
      "elapsed_ns": 16167,
      "error_map_descriptor_hash": "ac9f702a3c9a3903de6dc3c397e2ea2e5bf6fc3675b0aaf45d09a71545a5fd7e",
      "exact_expected_mapping_vector": [
        6,
        5,
        4,
        3,
        2,
        1,
        0
      ],
      "exact_minimum_gap_ulp_ratio": 0.03125,
      "expected_mapping_vector": [
        6,
        5,
        4,
        3,
        2,
        1,
        0
      ],
      "kind": "small-gap",
      "mapping_vector": [
        6,
        5,
        4,
        3,
        2,
        1,
        0
      ],
      "matches_expected": true,
      "mode": "descending_f64",
      "policy": "rust_fixed_exact_retained_binary64",
      "replay_index": 4,
      "row_hash": "71c6ee876e8703770d7bf47e29f359bd45abb544edc445997963d2998f4d6805",
      "simulation_execution_count": 0,
      "source_expected_mapping_vector": [
        6,
        5,
        4,
        3,
        0,
        1,
        2
      ],
      "total_simulated_shots": 0
    },
    {
      "case_id": "edge_0_1_m001ulp",
      "elapsed_ns": 15334,
      "error_map_descriptor_hash": "ac9f702a3c9a3903de6dc3c397e2ea2e5bf6fc3675b0aaf45d09a71545a5fd7e",
      "exact_expected_mapping_vector": [
        6,
        5,
        4,
        3,
        2,
        1,
        0
      ],
      "exact_minimum_gap_ulp_ratio": 0.03125,
      "expected_mapping_vector": [
        6,
        5,
        4,
        3,
        2,
        1,
        0
      ],
      "kind": "small-gap",
      "mapping_vector": [
        6,
        5,
        4,
        3,
        2,
        1,
        0
      ],
      "matches_expected": true,
      "mode": "descending_f64",
      "policy": "rust_fixed_exact_retained_binary64",
      "replay_index": 5,
      "row_hash": "056d2c9d7637f1cf408cdcd5140b8ef09f2f418546ab70b6f3a3c2b43c78aad8",
      "simulation_execution_count": 0,
      "source_expected_mapping_vector": [
        6,
        5,
        4,
        3,
        0,
        1,
        2
      ],
      "total_simulated_shots": 0
    },
    {
      "case_id": "edge_0_1_m001ulp",
      "elapsed_ns": 15250,
      "error_map_descriptor_hash": "ac9f702a3c9a3903de6dc3c397e2ea2e5bf6fc3675b0aaf45d09a71545a5fd7e",
      "exact_expected_mapping_vector": [
        6,
        5,
        4,
        3,
        2,
        1,
        0
      ],
      "exact_minimum_gap_ulp_ratio": 0.03125,
      "expected_mapping_vector": [
        6,
        5,
        4,
        3,
        2,
        1,
        0
      ],
      "kind": "small-gap",
      "mapping_vector": [
        6,
        5,
        4,
        3,
        2,
        1,
        0
      ],
      "matches_expected": true,
      "mode": "descending_f64",
      "policy": "rust_fixed_exact_retained_binary64",
      "replay_index": 6,
      "row_hash": "857c733f855f71b8fe9a5db43862bf605ae65ef182ed383d699b3f9fc58b9e43",
      "simulation_execution_count": 0,
      "source_expected_mapping_vector": [
        6,
        5,
        4,
        3,
        0,
        1,
        2
      ],
      "total_simulated_shots": 0
    },
    {
      "case_id": "edge_0_1_m001ulp",
      "elapsed_ns": 14917,
      "error_map_descriptor_hash": "ac9f702a3c9a3903de6dc3c397e2ea2e5bf6fc3675b0aaf45d09a71545a5fd7e",
      "exact_expected_mapping_vector": [
        6,
        5,
        4,
        3,
        2,
        1,
        0
      ],
      "exact_minimum_gap_ulp_ratio": 0.03125,
      "expected_mapping_vector": [
        6,
        5,
        4,
        3,
        2,
        1,
        0
      ],
      "kind": "small-gap",
      "mapping_vector": [
        6,
        5,
        4,
        3,
        2,
        1,
        0
      ],
      "matches_expected": true,
      "mode": "descending_f64",
      "policy": "rust_fixed_exact_retained_binary64",
      "replay_index": 7,
      "row_hash": "bb158894b985d093738e65e55dfec6cda4f0d93a224daf3720bd64ae57a72251",
      "simulation_execution_count": 0,
      "source_expected_mapping_vector": [
        6,
        5,
        4,
        3,
        0,
        1,
        2
      ],
      "total_simulated_shots": 0
    },
    {
      "case_id": "edge_1_0_p001ulp",
      "elapsed_ns": 15583,
      "error_map_descriptor_hash": "7b3a90b7a114099c47dabbfdfa4b46f88d656257bedf36b6f49dd82b823f7a1f",
      "exact_expected_mapping_vector": [
        6,
        5,
        4,
        3,
        2,
        1,
        0
      ],
      "exact_minimum_gap_ulp_ratio": 0.09375,
      "expected_mapping_vector": [
        6,
        5,
        4,
        3,
        2,
        1,
        0
      ],
      "kind": "small-gap",
      "mapping_vector": [
        6,
        5,
        4,
        3,
        2,
        1,
        0
      ],
      "matches_expected": true,
      "mode": "descending_f64",
      "policy": "rust_fixed_exact_retained_binary64",
      "replay_index": 0,
      "row_hash": "910de7ee43bf636aa9f55caf50de591797d4401769571a27963944263d07022d",
      "simulation_execution_count": 0,
      "source_expected_mapping_vector": [
        6,
        5,
        4,
        3,
        0,
        1,
        2
      ],
      "total_simulated_shots": 0
    },
    {
      "case_id": "edge_1_0_p001ulp",
      "elapsed_ns": 15000,
      "error_map_descriptor_hash": "7b3a90b7a114099c47dabbfdfa4b46f88d656257bedf36b6f49dd82b823f7a1f",
      "exact_expected_mapping_vector": [
        6,
        5,
        4,
        3,
        2,
        1,
        0
      ],
      "exact_minimum_gap_ulp_ratio": 0.09375,
      "expected_mapping_vector": [
        6,
        5,
        4,
        3,
        2,
        1,
        0
      ],
      "kind": "small-gap",
      "mapping_vector": [
        6,
        5,
        4,
        3,
        2,
        1,
        0
      ],
      "matches_expected": true,
      "mode": "descending_f64",
      "policy": "rust_fixed_exact_retained_binary64",
      "replay_index": 1,
      "row_hash": "b4203f651c55b61528740c4f1d0e9a99763c60c93f9c0a39d590bbeca829732f",
      "simulation_execution_count": 0,
      "source_expected_mapping_vector": [
        6,
        5,
        4,
        3,
        0,
        1,
        2
      ],
      "total_simulated_shots": 0
    },
    {
      "case_id": "edge_1_0_p001ulp",
      "elapsed_ns": 14916,
      "error_map_descriptor_hash": "7b3a90b7a114099c47dabbfdfa4b46f88d656257bedf36b6f49dd82b823f7a1f",
      "exact_expected_mapping_vector": [
        6,
        5,
        4,
        3,
        2,
        1,
        0
      ],
      "exact_minimum_gap_ulp_ratio": 0.09375,
      "expected_mapping_vector": [
        6,
        5,
        4,
        3,
        2,
        1,
        0
      ],
      "kind": "small-gap",
      "mapping_vector": [
        6,
        5,
        4,
        3,
        2,
        1,
        0
      ],
      "matches_expected": true,
      "mode": "descending_f64",
      "policy": "rust_fixed_exact_retained_binary64",
      "replay_index": 2,
      "row_hash": "4bdfa401640c1afb7a7f67187ae18d7b6cc53779cab308ca925e8ea421dee189",
      "simulation_execution_count": 0,
      "source_expected_mapping_vector": [
        6,
        5,
        4,
        3,
        0,
        1,
        2
      ],
      "total_simulated_shots": 0
    },
    {
      "case_id": "edge_1_0_p001ulp",
      "elapsed_ns": 14833,
      "error_map_descriptor_hash": "7b3a90b7a114099c47dabbfdfa4b46f88d656257bedf36b6f49dd82b823f7a1f",
      "exact_expected_mapping_vector": [
        6,
        5,
        4,
        3,
        2,
        1,
        0
      ],
      "exact_minimum_gap_ulp_ratio": 0.09375,
      "expected_mapping_vector": [
        6,
        5,
        4,
        3,
        2,
        1,
        0
      ],
      "kind": "small-gap",
      "mapping_vector": [
        6,
        5,
        4,
        3,
        2,
        1,
        0
      ],
      "matches_expected": true,
      "mode": "descending_f64",
      "policy": "rust_fixed_exact_retained_binary64",
      "replay_index": 3,
      "row_hash": "634aa5f6790b9dcc4de011947b030d5996115d5ad5c6f80a8221e0e7017ba91b",
      "simulation_execution_count": 0,
      "source_expected_mapping_vector": [
        6,
        5,
        4,
        3,
        0,
        1,
        2
      ],
      "total_simulated_shots": 0
    },
    {
      "case_id": "edge_1_0_p001ulp",
      "elapsed_ns": 14750,
      "error_map_descriptor_hash": "7b3a90b7a114099c47dabbfdfa4b46f88d656257bedf36b6f49dd82b823f7a1f",
      "exact_expected_mapping_vector": [
        6,
        5,
        4,
        3,
        2,
        1,
        0
      ],
      "exact_minimum_gap_ulp_ratio": 0.09375,
      "expected_mapping_vector": [
        6,
        5,
        4,
        3,
        2,
        1,
        0
      ],
      "kind": "small-gap",
      "mapping_vector": [
        6,
        5,
        4,
        3,
        2,
        1,
        0
      ],
      "matches_expected": true,
      "mode": "descending_f64",
      "policy": "rust_fixed_exact_retained_binary64",
      "replay_index": 4,
      "row_hash": "d629ad9d6366f6bee00ab3e3ecec95496fcbd4d8675640db8559cb0363929d6d",
      "simulation_execution_count": 0,
      "source_expected_mapping_vector": [
        6,
        5,
        4,
        3,
        0,
        1,
        2
      ],
      "total_simulated_shots": 0
    },
    {
      "case_id": "edge_1_0_p001ulp",
      "elapsed_ns": 14917,
      "error_map_descriptor_hash": "7b3a90b7a114099c47dabbfdfa4b46f88d656257bedf36b6f49dd82b823f7a1f",
      "exact_expected_mapping_vector": [
        6,
        5,
        4,
        3,
        2,
        1,
        0
      ],
      "exact_minimum_gap_ulp_ratio": 0.09375,
      "expected_mapping_vector": [
        6,
        5,
        4,
        3,
        2,
        1,
        0
      ],
      "kind": "small-gap",
      "mapping_vector": [
        6,
        5,
        4,
        3,
        2,
        1,
        0
      ],
      "matches_expected": true,
      "mode": "descending_f64",
      "policy": "rust_fixed_exact_retained_binary64",
      "replay_index": 5,
      "row_hash": "0cd0a8e97578884b97c328dbc87619c2d55705c7374c8107fbb1f603d3388149",
      "simulation_execution_count": 0,
      "source_expected_mapping_vector": [
        6,
        5,
        4,
        3,
        0,
        1,
        2
      ],
      "total_simulated_shots": 0
    },
    {
      "case_id": "edge_1_0_p001ulp",
      "elapsed_ns": 14750,
      "error_map_descriptor_hash": "7b3a90b7a114099c47dabbfdfa4b46f88d656257bedf36b6f49dd82b823f7a1f",
      "exact_expected_mapping_vector": [
        6,
        5,
        4,
        3,
        2,
        1,
        0
      ],
      "exact_minimum_gap_ulp_ratio": 0.09375,
      "expected_mapping_vector": [
        6,
        5,
        4,
        3,
        2,
        1,
        0
      ],
      "kind": "small-gap",
      "mapping_vector": [
        6,
        5,
        4,
        3,
        2,
        1,
        0
      ],
      "matches_expected": true,
      "mode": "descending_f64",
      "policy": "rust_fixed_exact_retained_binary64",
      "replay_index": 6,
      "row_hash": "e36828f4ae21bd97679d7a6b68ba5c7acbdb0d03e26d8b71aed219b06a639461",
      "simulation_execution_count": 0,
      "source_expected_mapping_vector": [
        6,
        5,
        4,
        3,
        0,
        1,
        2
      ],
      "total_simulated_shots": 0
    },
    {
      "case_id": "edge_1_0_p001ulp",
      "elapsed_ns": 14708,
      "error_map_descriptor_hash": "7b3a90b7a114099c47dabbfdfa4b46f88d656257bedf36b6f49dd82b823f7a1f",
      "exact_expected_mapping_vector": [
        6,
        5,
        4,
        3,
        2,
        1,
        0
      ],
      "exact_minimum_gap_ulp_ratio": 0.09375,
      "expected_mapping_vector": [
        6,
        5,
        4,
        3,
        2,
        1,
        0
      ],
      "kind": "small-gap",
      "mapping_vector": [
        6,
        5,
        4,
        3,
        2,
        1,
        0
      ],
      "matches_expected": true,
      "mode": "descending_f64",
      "policy": "rust_fixed_exact_retained_binary64",
      "replay_index": 7,
      "row_hash": "7fc00c4ecb504d4fee5327221046507705b5ad85d3b8b6f0f82fc8cfac7abc55",
      "simulation_execution_count": 0,
      "source_expected_mapping_vector": [
        6,
        5,
        4,
        3,
        0,
        1,
        2
      ],
      "total_simulated_shots": 0
    },
    {
      "case_id": "edge_1_0_p008ulp",
      "elapsed_ns": 15375,
      "error_map_descriptor_hash": "441dfa7ece0f3d62c95806c5b4909107f3561aada3f54d2bb9a0a40c0f4f013b",
      "exact_expected_mapping_vector": [
        6,
        5,
        4,
        3,
        2,
        1,
        0
      ],
      "exact_minimum_gap_ulp_ratio": 0.5,
      "expected_mapping_vector": [
        6,
        5,
        4,
        3,
        2,
        1,
        0
      ],
      "kind": "small-gap",
      "mapping_vector": [
        6,
        5,
        4,
        3,
        2,
        1,
        0
      ],
      "matches_expected": true,
      "mode": "descending_f64",
      "policy": "rust_fixed_exact_retained_binary64",
      "replay_index": 0,
      "row_hash": "6555315265a5b990d9874c7028a2a41aa0dbda4c891549295d49f9c6af8aeabc",
      "simulation_execution_count": 0,
      "source_expected_mapping_vector": [
        6,
        5,
        4,
        3,
        0,
        1,
        2
      ],
      "total_simulated_shots": 0
    },
    {
      "case_id": "edge_1_0_p008ulp",
      "elapsed_ns": 14834,
      "error_map_descriptor_hash": "441dfa7ece0f3d62c95806c5b4909107f3561aada3f54d2bb9a0a40c0f4f013b",
      "exact_expected_mapping_vector": [
        6,
        5,
        4,
        3,
        2,
        1,
        0
      ],
      "exact_minimum_gap_ulp_ratio": 0.5,
      "expected_mapping_vector": [
        6,
        5,
        4,
        3,
        2,
        1,
        0
      ],
      "kind": "small-gap",
      "mapping_vector": [
        6,
        5,
        4,
        3,
        2,
        1,
        0
      ],
      "matches_expected": true,
      "mode": "descending_f64",
      "policy": "rust_fixed_exact_retained_binary64",
      "replay_index": 1,
      "row_hash": "9cce7a266b1703adce35a64ffda664d8fc26dedaa12b5e4beec82f02a16d8e55",
      "simulation_execution_count": 0,
      "source_expected_mapping_vector": [
        6,
        5,
        4,
        3,
        0,
        1,
        2
      ],
      "total_simulated_shots": 0
    },
    {
      "case_id": "edge_1_0_p008ulp",
      "elapsed_ns": 14709,
      "error_map_descriptor_hash": "441dfa7ece0f3d62c95806c5b4909107f3561aada3f54d2bb9a0a40c0f4f013b",
      "exact_expected_mapping_vector": [
        6,
        5,
        4,
        3,
        2,
        1,
        0
      ],
      "exact_minimum_gap_ulp_ratio": 0.5,
      "expected_mapping_vector": [
        6,
        5,
        4,
        3,
        2,
        1,
        0
      ],
      "kind": "small-gap",
      "mapping_vector": [
        6,
        5,
        4,
        3,
        2,
        1,
        0
      ],
      "matches_expected": true,
      "mode": "descending_f64",
      "policy": "rust_fixed_exact_retained_binary64",
      "replay_index": 2,
      "row_hash": "262585b04b9dd769a8c3e17a6ea04489d0c3187f9c63a8daf46c7ef57e2d114f",
      "simulation_execution_count": 0,
      "source_expected_mapping_vector": [
        6,
        5,
        4,
        3,
        0,
        1,
        2
      ],
      "total_simulated_shots": 0
    },
    {
      "case_id": "edge_1_0_p008ulp",
      "elapsed_ns": 14792,
      "error_map_descriptor_hash": "441dfa7ece0f3d62c95806c5b4909107f3561aada3f54d2bb9a0a40c0f4f013b",
      "exact_expected_mapping_vector": [
        6,
        5,
        4,
        3,
        2,
        1,
        0
      ],
      "exact_minimum_gap_ulp_ratio": 0.5,
      "expected_mapping_vector": [
        6,
        5,
        4,
        3,
        2,
        1,
        0
      ],
      "kind": "small-gap",
      "mapping_vector": [
        6,
        5,
        4,
        3,
        2,
        1,
        0
      ],
      "matches_expected": true,
      "mode": "descending_f64",
      "policy": "rust_fixed_exact_retained_binary64",
      "replay_index": 3,
      "row_hash": "483b7f76f1a21b42a1a6528725b9ee92fe34e118940a491ca67dc137fdcfede3",
      "simulation_execution_count": 0,
      "source_expected_mapping_vector": [
        6,
        5,
        4,
        3,
        0,
        1,
        2
      ],
      "total_simulated_shots": 0
    },
    {
      "case_id": "edge_1_0_p008ulp",
      "elapsed_ns": 14667,
      "error_map_descriptor_hash": "441dfa7ece0f3d62c95806c5b4909107f3561aada3f54d2bb9a0a40c0f4f013b",
      "exact_expected_mapping_vector": [
        6,
        5,
        4,
        3,
        2,
        1,
        0
      ],
      "exact_minimum_gap_ulp_ratio": 0.5,
      "expected_mapping_vector": [
        6,
        5,
        4,
        3,
        2,
        1,
        0
      ],
      "kind": "small-gap",
      "mapping_vector": [
        6,
        5,
        4,
        3,
        2,
        1,
        0
      ],
      "matches_expected": true,
      "mode": "descending_f64",
      "policy": "rust_fixed_exact_retained_binary64",
      "replay_index": 4,
      "row_hash": "547429b596ba28dd3a2b1cef9162156597446624dc1a1473f3f02e8714096b09",
      "simulation_execution_count": 0,
      "source_expected_mapping_vector": [
        6,
        5,
        4,
        3,
        0,
        1,
        2
      ],
      "total_simulated_shots": 0
    },
    {
      "case_id": "edge_1_0_p008ulp",
      "elapsed_ns": 14750,
      "error_map_descriptor_hash": "441dfa7ece0f3d62c95806c5b4909107f3561aada3f54d2bb9a0a40c0f4f013b",
      "exact_expected_mapping_vector": [
        6,
        5,
        4,
        3,
        2,
        1,
        0
      ],
      "exact_minimum_gap_ulp_ratio": 0.5,
      "expected_mapping_vector": [
        6,
        5,
        4,
        3,
        2,
        1,
        0
      ],
      "kind": "small-gap",
      "mapping_vector": [
        6,
        5,
        4,
        3,
        2,
        1,
        0
      ],
      "matches_expected": true,
      "mode": "descending_f64",
      "policy": "rust_fixed_exact_retained_binary64",
      "replay_index": 5,
      "row_hash": "3845af81d827fc2531966f4a059b2a835d654681d4f4e6871a93af57dff4a1b3",
      "simulation_execution_count": 0,
      "source_expected_mapping_vector": [
        6,
        5,
        4,
        3,
        0,
        1,
        2
      ],
      "total_simulated_shots": 0
    },
    {
      "case_id": "edge_1_0_p008ulp",
      "elapsed_ns": 14792,
      "error_map_descriptor_hash": "441dfa7ece0f3d62c95806c5b4909107f3561aada3f54d2bb9a0a40c0f4f013b",
      "exact_expected_mapping_vector": [
        6,
        5,
        4,
        3,
        2,
        1,
        0
      ],
      "exact_minimum_gap_ulp_ratio": 0.5,
      "expected_mapping_vector": [
        6,
        5,
        4,
        3,
        2,
        1,
        0
      ],
      "kind": "small-gap",
      "mapping_vector": [
        6,
        5,
        4,
        3,
        2,
        1,
        0
      ],
      "matches_expected": true,
      "mode": "descending_f64",
      "policy": "rust_fixed_exact_retained_binary64",
      "replay_index": 6,
      "row_hash": "b381235d62c749a48c4608b4b818c93e8294aea64b3b0627381843446b5e5da6",
      "simulation_execution_count": 0,
      "source_expected_mapping_vector": [
        6,
        5,
        4,
        3,
        0,
        1,
        2
      ],
      "total_simulated_shots": 0
    },
    {
      "case_id": "edge_1_0_p008ulp",
      "elapsed_ns": 14750,
      "error_map_descriptor_hash": "441dfa7ece0f3d62c95806c5b4909107f3561aada3f54d2bb9a0a40c0f4f013b",
      "exact_expected_mapping_vector": [
        6,
        5,
        4,
        3,
        2,
        1,
        0
      ],
      "exact_minimum_gap_ulp_ratio": 0.5,
      "expected_mapping_vector": [
        6,
        5,
        4,
        3,
        2,
        1,
        0
      ],
      "kind": "small-gap",
      "mapping_vector": [
        6,
        5,
        4,
        3,
        2,
        1,
        0
      ],
      "matches_expected": true,
      "mode": "descending_f64",
      "policy": "rust_fixed_exact_retained_binary64",
      "replay_index": 7,
      "row_hash": "6f59d1d81665fb3eb0fed0f65bb2d9500dde1376cf49ef4dbb05180734f1e53f",
      "simulation_execution_count": 0,
      "source_expected_mapping_vector": [
        6,
        5,
        4,
        3,
        0,
        1,
        2
      ],
      "total_simulated_shots": 0
    },
    {
      "case_id": "edge_1_2_m001ulp",
      "elapsed_ns": 15208,
      "error_map_descriptor_hash": "4da96593d8d5f960413c4d60ddc9753e7e54024d523f5f69f2758a6360d33f5e",
      "exact_expected_mapping_vector": [
        6,
        5,
        4,
        3,
        2,
        1,
        0
      ],
      "exact_minimum_gap_ulp_ratio": 0.046875,
      "expected_mapping_vector": [
        6,
        5,
        4,
        3,
        2,
        1,
        0
      ],
      "kind": "small-gap",
      "mapping_vector": [
        6,
        5,
        4,
        3,
        2,
        1,
        0
      ],
      "matches_expected": true,
      "mode": "descending_f64",
      "policy": "rust_fixed_exact_retained_binary64",
      "replay_index": 0,
      "row_hash": "178229cc2aec718605d0c55189e01d8cf9d0b086141ed09740e03032f4504810",
      "simulation_execution_count": 0,
      "source_expected_mapping_vector": [
        6,
        5,
        4,
        3,
        0,
        1,
        2
      ],
      "total_simulated_shots": 0
    },
    {
      "case_id": "edge_1_2_m001ulp",
      "elapsed_ns": 14833,
      "error_map_descriptor_hash": "4da96593d8d5f960413c4d60ddc9753e7e54024d523f5f69f2758a6360d33f5e",
      "exact_expected_mapping_vector": [
        6,
        5,
        4,
        3,
        2,
        1,
        0
      ],
      "exact_minimum_gap_ulp_ratio": 0.046875,
      "expected_mapping_vector": [
        6,
        5,
        4,
        3,
        2,
        1,
        0
      ],
      "kind": "small-gap",
      "mapping_vector": [
        6,
        5,
        4,
        3,
        2,
        1,
        0
      ],
      "matches_expected": true,
      "mode": "descending_f64",
      "policy": "rust_fixed_exact_retained_binary64",
      "replay_index": 1,
      "row_hash": "f0892fc1e22c60616c494b997eac853d788facbef6dc6b5c88ffb4f3c96ac481",
      "simulation_execution_count": 0,
      "source_expected_mapping_vector": [
        6,
        5,
        4,
        3,
        0,
        1,
        2
      ],
      "total_simulated_shots": 0
    },
    {
      "case_id": "edge_1_2_m001ulp",
      "elapsed_ns": 14750,
      "error_map_descriptor_hash": "4da96593d8d5f960413c4d60ddc9753e7e54024d523f5f69f2758a6360d33f5e",
      "exact_expected_mapping_vector": [
        6,
        5,
        4,
        3,
        2,
        1,
        0
      ],
      "exact_minimum_gap_ulp_ratio": 0.046875,
      "expected_mapping_vector": [
        6,
        5,
        4,
        3,
        2,
        1,
        0
      ],
      "kind": "small-gap",
      "mapping_vector": [
        6,
        5,
        4,
        3,
        2,
        1,
        0
      ],
      "matches_expected": true,
      "mode": "descending_f64",
      "policy": "rust_fixed_exact_retained_binary64",
      "replay_index": 2,
      "row_hash": "22c22e448ba5d61780be5b46a4ea6da3f3e768d2c21d2e3aa2223bd4870b55ae",
      "simulation_execution_count": 0,
      "source_expected_mapping_vector": [
        6,
        5,
        4,
        3,
        0,
        1,
        2
      ],
      "total_simulated_shots": 0
    },
    {
      "case_id": "edge_1_2_m001ulp",
      "elapsed_ns": 14666,
      "error_map_descriptor_hash": "4da96593d8d5f960413c4d60ddc9753e7e54024d523f5f69f2758a6360d33f5e",
      "exact_expected_mapping_vector": [
        6,
        5,
        4,
        3,
        2,
        1,
        0
      ],
      "exact_minimum_gap_ulp_ratio": 0.046875,
      "expected_mapping_vector": [
        6,
        5,
        4,
        3,
        2,
        1,
        0
      ],
      "kind": "small-gap",
      "mapping_vector": [
        6,
        5,
        4,
        3,
        2,
        1,
        0
      ],
      "matches_expected": true,
      "mode": "descending_f64",
      "policy": "rust_fixed_exact_retained_binary64",
      "replay_index": 3,
      "row_hash": "e49b389ec5b7de98af402bc648506c2f386f506d57570e18ae6ba0f9f1412549",
      "simulation_execution_count": 0,
      "source_expected_mapping_vector": [
        6,
        5,
        4,
        3,
        0,
        1,
        2
      ],
      "total_simulated_shots": 0
    },
    {
      "case_id": "edge_1_2_m001ulp",
      "elapsed_ns": 14750,
      "error_map_descriptor_hash": "4da96593d8d5f960413c4d60ddc9753e7e54024d523f5f69f2758a6360d33f5e",
      "exact_expected_mapping_vector": [
        6,
        5,
        4,
        3,
        2,
        1,
        0
      ],
      "exact_minimum_gap_ulp_ratio": 0.046875,
      "expected_mapping_vector": [
        6,
        5,
        4,
        3,
        2,
        1,
        0
      ],
      "kind": "small-gap",
      "mapping_vector": [
        6,
        5,
        4,
        3,
        2,
        1,
        0
      ],
      "matches_expected": true,
      "mode": "descending_f64",
      "policy": "rust_fixed_exact_retained_binary64",
      "replay_index": 4,
      "row_hash": "5449c9a4b5dd4ef9ba8b7343cb5a8b7c9b88e625061da34b241936badd4c9117",
      "simulation_execution_count": 0,
      "source_expected_mapping_vector": [
        6,
        5,
        4,
        3,
        0,
        1,
        2
      ],
      "total_simulated_shots": 0
    },
    {
      "case_id": "edge_1_2_m001ulp",
      "elapsed_ns": 14834,
      "error_map_descriptor_hash": "4da96593d8d5f960413c4d60ddc9753e7e54024d523f5f69f2758a6360d33f5e",
      "exact_expected_mapping_vector": [
        6,
        5,
        4,
        3,
        2,
        1,
        0
      ],
      "exact_minimum_gap_ulp_ratio": 0.046875,
      "expected_mapping_vector": [
        6,
        5,
        4,
        3,
        2,
        1,
        0
      ],
      "kind": "small-gap",
      "mapping_vector": [
        6,
        5,
        4,
        3,
        2,
        1,
        0
      ],
      "matches_expected": true,
      "mode": "descending_f64",
      "policy": "rust_fixed_exact_retained_binary64",
      "replay_index": 5,
      "row_hash": "bbd2eaaacc126022d2f249a0c53d742c391baed170e1171ee92f2b51cf4b8411",
      "simulation_execution_count": 0,
      "source_expected_mapping_vector": [
        6,
        5,
        4,
        3,
        0,
        1,
        2
      ],
      "total_simulated_shots": 0
    },
    {
      "case_id": "edge_1_2_m001ulp",
      "elapsed_ns": 14875,
      "error_map_descriptor_hash": "4da96593d8d5f960413c4d60ddc9753e7e54024d523f5f69f2758a6360d33f5e",
      "exact_expected_mapping_vector": [
        6,
        5,
        4,
        3,
        2,
        1,
        0
      ],
      "exact_minimum_gap_ulp_ratio": 0.046875,
      "expected_mapping_vector": [
        6,
        5,
        4,
        3,
        2,
        1,
        0
      ],
      "kind": "small-gap",
      "mapping_vector": [
        6,
        5,
        4,
        3,
        2,
        1,
        0
      ],
      "matches_expected": true,
      "mode": "descending_f64",
      "policy": "rust_fixed_exact_retained_binary64",
      "replay_index": 6,
      "row_hash": "673aad922c8427a069a1d1ec6dd7a27112d7105173ef1594360b1984b5f58e1f",
      "simulation_execution_count": 0,
      "source_expected_mapping_vector": [
        6,
        5,
        4,
        3,
        0,
        1,
        2
      ],
      "total_simulated_shots": 0
    },
    {
      "case_id": "edge_1_2_m001ulp",
      "elapsed_ns": 14791,
      "error_map_descriptor_hash": "4da96593d8d5f960413c4d60ddc9753e7e54024d523f5f69f2758a6360d33f5e",
      "exact_expected_mapping_vector": [
        6,
        5,
        4,
        3,
        2,
        1,
        0
      ],
      "exact_minimum_gap_ulp_ratio": 0.046875,
      "expected_mapping_vector": [
        6,
        5,
        4,
        3,
        2,
        1,
        0
      ],
      "kind": "small-gap",
      "mapping_vector": [
        6,
        5,
        4,
        3,
        2,
        1,
        0
      ],
      "matches_expected": true,
      "mode": "descending_f64",
      "policy": "rust_fixed_exact_retained_binary64",
      "replay_index": 7,
      "row_hash": "85d4a58d2946869ac1aff105f2a187fe2634cc1419fbc774f5633f6f23a9af07",
      "simulation_execution_count": 0,
      "source_expected_mapping_vector": [
        6,
        5,
        4,
        3,
        0,
        1,
        2
      ],
      "total_simulated_shots": 0
    },
    {
      "case_id": "edge_2_1_p001ulp",
      "elapsed_ns": 15125,
      "error_map_descriptor_hash": "6f857c86da7e8c5cf82806f3361aa4a9b2467bc8982ef8f97d61178ee46bf13d",
      "exact_expected_mapping_vector": [
        6,
        5,
        4,
        3,
        2,
        1,
        0
      ],
      "exact_minimum_gap_ulp_ratio": 0.046875,
      "expected_mapping_vector": [
        6,
        5,
        4,
        3,
        2,
        1,
        0
      ],
      "kind": "small-gap",
      "mapping_vector": [
        6,
        5,
        4,
        3,
        2,
        1,
        0
      ],
      "matches_expected": true,
      "mode": "descending_f64",
      "policy": "rust_fixed_exact_retained_binary64",
      "replay_index": 0,
      "row_hash": "f5da9a87fb8bbff946d3bd918a085f997d4927e7484a247514982dd3ebd5860d",
      "simulation_execution_count": 0,
      "source_expected_mapping_vector": [
        6,
        5,
        4,
        3,
        0,
        1,
        2
      ],
      "total_simulated_shots": 0
    },
    {
      "case_id": "edge_2_1_p001ulp",
      "elapsed_ns": 14917,
      "error_map_descriptor_hash": "6f857c86da7e8c5cf82806f3361aa4a9b2467bc8982ef8f97d61178ee46bf13d",
      "exact_expected_mapping_vector": [
        6,
        5,
        4,
        3,
        2,
        1,
        0
      ],
      "exact_minimum_gap_ulp_ratio": 0.046875,
      "expected_mapping_vector": [
        6,
        5,
        4,
        3,
        2,
        1,
        0
      ],
      "kind": "small-gap",
      "mapping_vector": [
        6,
        5,
        4,
        3,
        2,
        1,
        0
      ],
      "matches_expected": true,
      "mode": "descending_f64",
      "policy": "rust_fixed_exact_retained_binary64",
      "replay_index": 1,
      "row_hash": "cbdd09c8b513154a7eda7aa24b33e44e4b287bb95ca40fc595164776a422a817",
      "simulation_execution_count": 0,
      "source_expected_mapping_vector": [
        6,
        5,
        4,
        3,
        0,
        1,
        2
      ],
      "total_simulated_shots": 0
    },
    {
      "case_id": "edge_2_1_p001ulp",
      "elapsed_ns": 14708,
      "error_map_descriptor_hash": "6f857c86da7e8c5cf82806f3361aa4a9b2467bc8982ef8f97d61178ee46bf13d",
      "exact_expected_mapping_vector": [
        6,
        5,
        4,
        3,
        2,
        1,
        0
      ],
      "exact_minimum_gap_ulp_ratio": 0.046875,
      "expected_mapping_vector": [
        6,
        5,
        4,
        3,
        2,
        1,
        0
      ],
      "kind": "small-gap",
      "mapping_vector": [
        6,
        5,
        4,
        3,
        2,
        1,
        0
      ],
      "matches_expected": true,
      "mode": "descending_f64",
      "policy": "rust_fixed_exact_retained_binary64",
      "replay_index": 2,
      "row_hash": "fa730f0af09b5a68f27d6833c29b6d71bbc74c3c3df11180e8ca8112450f3d21",
      "simulation_execution_count": 0,
      "source_expected_mapping_vector": [
        6,
        5,
        4,
        3,
        0,
        1,
        2
      ],
      "total_simulated_shots": 0
    },
    {
      "case_id": "edge_2_1_p001ulp",
      "elapsed_ns": 14833,
      "error_map_descriptor_hash": "6f857c86da7e8c5cf82806f3361aa4a9b2467bc8982ef8f97d61178ee46bf13d",
      "exact_expected_mapping_vector": [
        6,
        5,
        4,
        3,
        2,
        1,
        0
      ],
      "exact_minimum_gap_ulp_ratio": 0.046875,
      "expected_mapping_vector": [
        6,
        5,
        4,
        3,
        2,
        1,
        0
      ],
      "kind": "small-gap",
      "mapping_vector": [
        6,
        5,
        4,
        3,
        2,
        1,
        0
      ],
      "matches_expected": true,
      "mode": "descending_f64",
      "policy": "rust_fixed_exact_retained_binary64",
      "replay_index": 3,
      "row_hash": "abf4a97f8102b994146d579b9c647033fe67e662948b793bc587ea819d58b542",
      "simulation_execution_count": 0,
      "source_expected_mapping_vector": [
        6,
        5,
        4,
        3,
        0,
        1,
        2
      ],
      "total_simulated_shots": 0
    },
    {
      "case_id": "edge_2_1_p001ulp",
      "elapsed_ns": 14792,
      "error_map_descriptor_hash": "6f857c86da7e8c5cf82806f3361aa4a9b2467bc8982ef8f97d61178ee46bf13d",
      "exact_expected_mapping_vector": [
        6,
        5,
        4,
        3,
        2,
        1,
        0
      ],
      "exact_minimum_gap_ulp_ratio": 0.046875,
      "expected_mapping_vector": [
        6,
        5,
        4,
        3,
        2,
        1,
        0
      ],
      "kind": "small-gap",
      "mapping_vector": [
        6,
        5,
        4,
        3,
        2,
        1,
        0
      ],
      "matches_expected": true,
      "mode": "descending_f64",
      "policy": "rust_fixed_exact_retained_binary64",
      "replay_index": 4,
      "row_hash": "5898fbe4ff2e9f37b2e8806453da44ea78a57f0512da0963667ddd4fa5ee346e",
      "simulation_execution_count": 0,
      "source_expected_mapping_vector": [
        6,
        5,
        4,
        3,
        0,
        1,
        2
      ],
      "total_simulated_shots": 0
    },
    {
      "case_id": "edge_2_1_p001ulp",
      "elapsed_ns": 14667,
      "error_map_descriptor_hash": "6f857c86da7e8c5cf82806f3361aa4a9b2467bc8982ef8f97d61178ee46bf13d",
      "exact_expected_mapping_vector": [
        6,
        5,
        4,
        3,
        2,
        1,
        0
      ],
      "exact_minimum_gap_ulp_ratio": 0.046875,
      "expected_mapping_vector": [
        6,
        5,
        4,
        3,
        2,
        1,
        0
      ],
      "kind": "small-gap",
      "mapping_vector": [
        6,
        5,
        4,
        3,
        2,
        1,
        0
      ],
      "matches_expected": true,
      "mode": "descending_f64",
      "policy": "rust_fixed_exact_retained_binary64",
      "replay_index": 5,
      "row_hash": "23e6cbe37bc09c03dcc910c977ea3fcf8e51861478bfbed6e91ffc3ab4929932",
      "simulation_execution_count": 0,
      "source_expected_mapping_vector": [
        6,
        5,
        4,
        3,
        0,
        1,
        2
      ],
      "total_simulated_shots": 0
    },
    {
      "case_id": "edge_2_1_p001ulp",
      "elapsed_ns": 14750,
      "error_map_descriptor_hash": "6f857c86da7e8c5cf82806f3361aa4a9b2467bc8982ef8f97d61178ee46bf13d",
      "exact_expected_mapping_vector": [
        6,
        5,
        4,
        3,
        2,
        1,
        0
      ],
      "exact_minimum_gap_ulp_ratio": 0.046875,
      "expected_mapping_vector": [
        6,
        5,
        4,
        3,
        2,
        1,
        0
      ],
      "kind": "small-gap",
      "mapping_vector": [
        6,
        5,
        4,
        3,
        2,
        1,
        0
      ],
      "matches_expected": true,
      "mode": "descending_f64",
      "policy": "rust_fixed_exact_retained_binary64",
      "replay_index": 6,
      "row_hash": "8313e07f1931f651ac5a2c9a8a71240d1c03e8966a072e1eb611681715debce3",
      "simulation_execution_count": 0,
      "source_expected_mapping_vector": [
        6,
        5,
        4,
        3,
        0,
        1,
        2
      ],
      "total_simulated_shots": 0
    },
    {
      "case_id": "edge_2_1_p001ulp",
      "elapsed_ns": 14750,
      "error_map_descriptor_hash": "6f857c86da7e8c5cf82806f3361aa4a9b2467bc8982ef8f97d61178ee46bf13d",
      "exact_expected_mapping_vector": [
        6,
        5,
        4,
        3,
        2,
        1,
        0
      ],
      "exact_minimum_gap_ulp_ratio": 0.046875,
      "expected_mapping_vector": [
        6,
        5,
        4,
        3,
        2,
        1,
        0
      ],
      "kind": "small-gap",
      "mapping_vector": [
        6,
        5,
        4,
        3,
        2,
        1,
        0
      ],
      "matches_expected": true,
      "mode": "descending_f64",
      "policy": "rust_fixed_exact_retained_binary64",
      "replay_index": 7,
      "row_hash": "ecef929a1de3619363b0ad321e5be087dca442e863e866f0ed346c6b0d4a41d3",
      "simulation_execution_count": 0,
      "source_expected_mapping_vector": [
        6,
        5,
        4,
        3,
        0,
        1,
        2
      ],
      "total_simulated_shots": 0
    },
    {
      "case_id": "edge_2_1_p008ulp",
      "elapsed_ns": 15083,
      "error_map_descriptor_hash": "0ba8e42c6e27d10c2ced128b6018016803d09ba9ad7221062d5a24f504e85cd1",
      "exact_expected_mapping_vector": [
        6,
        5,
        4,
        3,
        2,
        1,
        0
      ],
      "exact_minimum_gap_ulp_ratio": 0.25,
      "expected_mapping_vector": [
        6,
        5,
        4,
        3,
        2,
        1,
        0
      ],
      "kind": "small-gap",
      "mapping_vector": [
        6,
        5,
        4,
        3,
        2,
        1,
        0
      ],
      "matches_expected": true,
      "mode": "descending_f64",
      "policy": "rust_fixed_exact_retained_binary64",
      "replay_index": 0,
      "row_hash": "b3beb9dbcbd1f011e1fd5e907a89934b1c668094c201fcf1cda8dca76658950e",
      "simulation_execution_count": 0,
      "source_expected_mapping_vector": [
        6,
        5,
        4,
        3,
        0,
        1,
        2
      ],
      "total_simulated_shots": 0
    },
    {
      "case_id": "edge_2_1_p008ulp",
      "elapsed_ns": 14750,
      "error_map_descriptor_hash": "0ba8e42c6e27d10c2ced128b6018016803d09ba9ad7221062d5a24f504e85cd1",
      "exact_expected_mapping_vector": [
        6,
        5,
        4,
        3,
        2,
        1,
        0
      ],
      "exact_minimum_gap_ulp_ratio": 0.25,
      "expected_mapping_vector": [
        6,
        5,
        4,
        3,
        2,
        1,
        0
      ],
      "kind": "small-gap",
      "mapping_vector": [
        6,
        5,
        4,
        3,
        2,
        1,
        0
      ],
      "matches_expected": true,
      "mode": "descending_f64",
      "policy": "rust_fixed_exact_retained_binary64",
      "replay_index": 1,
      "row_hash": "a056e2631162cb70261f8395700fdd70af8f60f22f0f5f043868f75bd37d5a94",
      "simulation_execution_count": 0,
      "source_expected_mapping_vector": [
        6,
        5,
        4,
        3,
        0,
        1,
        2
      ],
      "total_simulated_shots": 0
    },
    {
      "case_id": "edge_2_1_p008ulp",
      "elapsed_ns": 14667,
      "error_map_descriptor_hash": "0ba8e42c6e27d10c2ced128b6018016803d09ba9ad7221062d5a24f504e85cd1",
      "exact_expected_mapping_vector": [
        6,
        5,
        4,
        3,
        2,
        1,
        0
      ],
      "exact_minimum_gap_ulp_ratio": 0.25,
      "expected_mapping_vector": [
        6,
        5,
        4,
        3,
        2,
        1,
        0
      ],
      "kind": "small-gap",
      "mapping_vector": [
        6,
        5,
        4,
        3,
        2,
        1,
        0
      ],
      "matches_expected": true,
      "mode": "descending_f64",
      "policy": "rust_fixed_exact_retained_binary64",
      "replay_index": 2,
      "row_hash": "222536354018d6fb7f4609582f43210287df96487c08acf7c20ac32b23112430",
      "simulation_execution_count": 0,
      "source_expected_mapping_vector": [
        6,
        5,
        4,
        3,
        0,
        1,
        2
      ],
      "total_simulated_shots": 0
    },
    {
      "case_id": "edge_2_1_p008ulp",
      "elapsed_ns": 14833,
      "error_map_descriptor_hash": "0ba8e42c6e27d10c2ced128b6018016803d09ba9ad7221062d5a24f504e85cd1",
      "exact_expected_mapping_vector": [
        6,
        5,
        4,
        3,
        2,
        1,
        0
      ],
      "exact_minimum_gap_ulp_ratio": 0.25,
      "expected_mapping_vector": [
        6,
        5,
        4,
        3,
        2,
        1,
        0
      ],
      "kind": "small-gap",
      "mapping_vector": [
        6,
        5,
        4,
        3,
        2,
        1,
        0
      ],
      "matches_expected": true,
      "mode": "descending_f64",
      "policy": "rust_fixed_exact_retained_binary64",
      "replay_index": 3,
      "row_hash": "44d0187862cb7ad6bc057a8cf2c320cd50d4bc733866f9bbaeef89ab71304dbd",
      "simulation_execution_count": 0,
      "source_expected_mapping_vector": [
        6,
        5,
        4,
        3,
        0,
        1,
        2
      ],
      "total_simulated_shots": 0
    },
    {
      "case_id": "edge_2_1_p008ulp",
      "elapsed_ns": 14792,
      "error_map_descriptor_hash": "0ba8e42c6e27d10c2ced128b6018016803d09ba9ad7221062d5a24f504e85cd1",
      "exact_expected_mapping_vector": [
        6,
        5,
        4,
        3,
        2,
        1,
        0
      ],
      "exact_minimum_gap_ulp_ratio": 0.25,
      "expected_mapping_vector": [
        6,
        5,
        4,
        3,
        2,
        1,
        0
      ],
      "kind": "small-gap",
      "mapping_vector": [
        6,
        5,
        4,
        3,
        2,
        1,
        0
      ],
      "matches_expected": true,
      "mode": "descending_f64",
      "policy": "rust_fixed_exact_retained_binary64",
      "replay_index": 4,
      "row_hash": "1bd5106dc5a24ae162d2690e58cbe2e2cc4f7e80f1d0d181452c9ae7b6bcaed6",
      "simulation_execution_count": 0,
      "source_expected_mapping_vector": [
        6,
        5,
        4,
        3,
        0,
        1,
        2
      ],
      "total_simulated_shots": 0
    },
    {
      "case_id": "edge_2_1_p008ulp",
      "elapsed_ns": 14708,
      "error_map_descriptor_hash": "0ba8e42c6e27d10c2ced128b6018016803d09ba9ad7221062d5a24f504e85cd1",
      "exact_expected_mapping_vector": [
        6,
        5,
        4,
        3,
        2,
        1,
        0
      ],
      "exact_minimum_gap_ulp_ratio": 0.25,
      "expected_mapping_vector": [
        6,
        5,
        4,
        3,
        2,
        1,
        0
      ],
      "kind": "small-gap",
      "mapping_vector": [
        6,
        5,
        4,
        3,
        2,
        1,
        0
      ],
      "matches_expected": true,
      "mode": "descending_f64",
      "policy": "rust_fixed_exact_retained_binary64",
      "replay_index": 5,
      "row_hash": "f73fc69f690c48e4673e01c5456424b50f888e880d7e46a6284598c40a3716c6",
      "simulation_execution_count": 0,
      "source_expected_mapping_vector": [
        6,
        5,
        4,
        3,
        0,
        1,
        2
      ],
      "total_simulated_shots": 0
    },
    {
      "case_id": "edge_2_1_p008ulp",
      "elapsed_ns": 14792,
      "error_map_descriptor_hash": "0ba8e42c6e27d10c2ced128b6018016803d09ba9ad7221062d5a24f504e85cd1",
      "exact_expected_mapping_vector": [
        6,
        5,
        4,
        3,
        2,
        1,
        0
      ],
      "exact_minimum_gap_ulp_ratio": 0.25,
      "expected_mapping_vector": [
        6,
        5,
        4,
        3,
        2,
        1,
        0
      ],
      "kind": "small-gap",
      "mapping_vector": [
        6,
        5,
        4,
        3,
        2,
        1,
        0
      ],
      "matches_expected": true,
      "mode": "descending_f64",
      "policy": "rust_fixed_exact_retained_binary64",
      "replay_index": 6,
      "row_hash": "fac626a642b6896f7c4872d36bfe37bd1e4140bd357fd52ca63c58a742253d41",
      "simulation_execution_count": 0,
      "source_expected_mapping_vector": [
        6,
        5,
        4,
        3,
        0,
        1,
        2
      ],
      "total_simulated_shots": 0
    },
    {
      "case_id": "edge_2_1_p008ulp",
      "elapsed_ns": 14666,
      "error_map_descriptor_hash": "0ba8e42c6e27d10c2ced128b6018016803d09ba9ad7221062d5a24f504e85cd1",
      "exact_expected_mapping_vector": [
        6,
        5,
        4,
        3,
        2,
        1,
        0
      ],
      "exact_minimum_gap_ulp_ratio": 0.25,
      "expected_mapping_vector": [
        6,
        5,
        4,
        3,
        2,
        1,
        0
      ],
      "kind": "small-gap",
      "mapping_vector": [
        6,
        5,
        4,
        3,
        2,
        1,
        0
      ],
      "matches_expected": true,
      "mode": "descending_f64",
      "policy": "rust_fixed_exact_retained_binary64",
      "replay_index": 7,
      "row_hash": "20cbacbd368811ba513d050ac0dc65aa9f9f13b0dbfb1b0eb8f0762650f9b1c1",
      "simulation_execution_count": 0,
      "source_expected_mapping_vector": [
        6,
        5,
        4,
        3,
        0,
        1,
        2
      ],
      "total_simulated_shots": 0
    }
  ],
  "simulation_execution_count": 0,
  "started_at_unix": 1784557573,
  "target_descriptor_sha256": "702c8fd9dcf67a069e7af63e31a57c74c17aaa5e3c5b6d8c2e28ec0c049c0de7",
  "total_simulated_shots": 0,
  "warmup_call_count": 16,
  "warmup_matches_expected": 16
}
